vrcar/__init__.py
vrcar/__main__.py
vrcar/_version.py
vrcar/common.py
vrcar/log.py
vrcar/client/__init__.py
vrcar/client/camera.py
vrcar/client/controls.py
vrcar/client/provider/pygame.py
vrcar/client/provider/openxr/__init__.py
vrcar/client/provider/openxr/plane.frag
vrcar/client/provider/openxr/plane.vert
vrcar/server/__init__.py
vrcar/server/camera.py
vrcar/server/controls.py
vrcar/server/motors.py
vrcar/server/pwm.py
vrcar/server/servos.py
vrcar-1.0.2.dist-info/METADATA
vrcar-1.0.2.dist-info/WHEEL
vrcar-1.0.2.dist-info/entry_points.txt
vrcar-1.0.2.dist-info/licenses/LICENSE
vrcar-1.0.2.dist-info/RECORD
