Metadata-Version: 2.3
Name: vrcar
Version: 1.0.2
Summary: VR controlled Raspberry Pi car
Project-URL: Documentation, https://github.com/Grub4K/vrcar
Project-URL: Issues, https://github.com/Grub4K/vrcar/issues
Project-URL: Source, https://github.com/Grub4K/vrcar
Author-email: Simon Sawicki <contact@grub4k.xyz>
License-Expression: MIT
License-File: LICENSE
Classifier: Development Status :: 4 - Beta
Classifier: Programming Language :: Python
Classifier: Programming Language :: Python :: 3.10
Classifier: Programming Language :: Python :: 3.11
Classifier: Programming Language :: Python :: 3.12
Classifier: Programming Language :: Python :: Implementation :: CPython
Requires-Python: >=3.10
Provides-Extra: pygame
Requires-Dist: pygame; extra == 'pygame'
Provides-Extra: vr
Requires-Dist: pillow; extra == 'vr'
Requires-Dist: pyopengl; extra == 'vr'
Requires-Dist: pyopenxr; extra == 'vr'
